LICENSE
MANIFEST.in
README.rst
setup.py
mediawiki_utilities.egg-info/PKG-INFO
mediawiki_utilities.egg-info/SOURCES.txt
mediawiki_utilities.egg-info/dependency_links.txt
mediawiki_utilities.egg-info/requires.txt
mediawiki_utilities.egg-info/top_level.txt
mw/__init__.py
mw/api/__init__.py
mw/api/errors.py
mw/api/session.py
mw/api/collections/__init__.py
mw/api/collections/collection.py
mw/api/collections/deleted_revisions.py
mw/api/collections/pages.py
mw/api/collections/recent_changes.py
mw/api/collections/revisions.py
mw/api/collections/site_info.py
mw/api/collections/user_contribs.py
mw/api/collections/users.py
mw/database/__init__.py
mw/database/db.py
mw/database/collections/__init__.py
mw/database/collections/collection.py
mw/database/collections/pages.py
mw/database/collections/recent_changes.py
mw/database/collections/revisions.py
mw/database/collections/users.py
mw/lib/__init__.py
mw/lib/persistence/__init__.py
mw/lib/persistence/api.py
mw/lib/persistence/defaults.py
mw/lib/persistence/difference.py
mw/lib/persistence/state.py
mw/lib/persistence/tokenization.py
mw/lib/persistence/tokens.py
mw/lib/persistence/tests/__init__.py
mw/lib/persistence/tests/test_difference.py
mw/lib/persistence/tests/test_state.py
mw/lib/persistence/tests/test_tokenization.py
mw/lib/persistence/tests/test_tokens.py
mw/lib/reverts/__init__.py
mw/lib/reverts/api.py
mw/lib/reverts/database.py
mw/lib/reverts/defaults.py
mw/lib/reverts/detector.py
mw/lib/reverts/dummy_checksum.py
mw/lib/reverts/functions.py
mw/lib/reverts/tests/__init__.py
mw/lib/reverts/tests/test_detector.py
mw/lib/reverts/tests/test_functions.py
mw/lib/sessions/__init__.py
mw/lib/sessions/cache.py
mw/lib/sessions/defaults.py
mw/lib/sessions/event.py
mw/lib/sessions/functions.py
mw/lib/sessions/tests/__init__.py
mw/lib/sessions/tests/test_cache.py
mw/lib/sessions/tests/test_functions.py
mw/lib/title/__init__.py
mw/lib/title/functions.py
mw/lib/title/parser.py
mw/lib/title/tests/__init__.py
mw/lib/title/tests/test_functions.py
mw/lib/title/tests/test_parser.py
mw/types/__init__.py
mw/types/namespace.py
mw/types/serializable.py
mw/types/timestamp.py
mw/types/tests/__init__.py
mw/types/tests/test_namespace.py
